fiftyone_mcp/__init__.py
fiftyone_mcp/config/settings.json
fiftyone_mcp/server.py
fiftyone_mcp/tools/__init__.py
fiftyone_mcp/tools/datasets.py
fiftyone_mcp/tools/operators.py
fiftyone_mcp/tools/plugins.py
fiftyone_mcp/tools/session.py
fiftyone_mcp/tools/utils.py
fiftyone_mcp_server-0.1.2.dist-info/METADATA
fiftyone_mcp_server-0.1.2.dist-info/WHEEL
fiftyone_mcp_server-0.1.2.dist-info/entry_points.txt
fiftyone_mcp_server-0.1.2.dist-info/RECORD
