Metadata-Version: 2.4
Name: fiftyone-mcp-server
Version: 0.1.2
Summary: MCP server exposing FiftyOne dataset analysis tools
License: MIT
Keywords: mcp,fiftyone,computer-vision,ai,datasets,model-context-protocol
Author: Adonai Vera
Author-email: adonai.vera@gmail.com
Requires-Python: >=3.10,<3.14
Classifier: Development Status :: 4 - Beta
Classifier: Intended Audience :: Developers
Classifier: Intended Audience :: Science/Research
Classifier: License :: OSI Approved :: MIT License
Classifier: Operating System :: OS Independent
Classifier: Programming Language :: Python :: 3
Classifier: Programming Language :: Python :: 3.10
Classifier: Programming Language :: Python :: 3.11
Classifier: Programming Language :: Python :: 3.12
Classifier: Programming Language :: Python :: 3.13
Classifier: Programming Language :: Python :: 3.9
Classifier: Topic :: Scientific/Engineering :: Artificial Intelligence
Requires-Dist: fiftyone (>=1.0,<2.0)
Requires-Dist: mcp (>=0.9.0,<0.10.0)
Requires-Dist: torch (>=2.9.1,<3.0.0)
Requires-Dist: torchvision (>=0.24.1,<0.25.0)
Requires-Dist: ultralytics (>=8.3.240,<9.0.0)
Project-URL: Documentation, https://github.com/AdonaiVera/fiftyone-mcp-server#readme
Project-URL: Homepage, https://github.com/AdonaiVera/fiftyone-mcp-server
Project-URL: Repository, https://github.com/AdonaiVera/fiftyone-mcp-server
